gaitmod/__init__.py
gaitmod/viz.py
gaitmod/configs/base_model_config.yaml
gaitmod/configs/classification_lstm_config.yaml
gaitmod/configs/data_preprocessing.yaml
gaitmod/configs/linearRegression_config.yaml
gaitmod/configs/logistic_regression_config.yaml
gaitmod/configs/regression_lstm_config.yaml
gaitmod/configs/written/lfp_metadata_config.yaml
gaitmod/models/base_model.py
gaitmod/models/classification_models.py
gaitmod/models/feature_extraction.py
gaitmod/models/lstm_classification_model.py
gaitmod/models/lstm_models.py
gaitmod/models/regression_models.py
gaitmod/tests/__init__.py
gaitmod/tests/test_data_processor.py
gaitmod/tests/test_feature_extractor.py
gaitmod/tests/test_file_reader.py
gaitmod/tests/test_model.py
gaitmod/utils/_file_reader.py
gaitmod/utils/data_processor.py
gaitmod/utils/feature_extractor.py
gaitmod/utils/file_reader.py
gaitmod/utils/utils.py
gaitmod-0.1.0.dist-info/licenses/LICENSE
gaitmod-0.1.0.dist-info/WHEEL
gaitmod-0.1.0.dist-info/METADATA
gaitmod-0.1.0.dist-info/RECORD
