Metadata-Version: 2.4
Name: gaitmod
Version: 0.1.0
Summary: real-time gait modulation prediction using multimodal neural and movement data (LFP, EEG, IMU, EMG) — designed for closed-loop DBS systems in Parkinson's diseas.
Keywords: gait,modulation,LFP,ML
Author-email: Mohammad Orabe <orabe.mhd@gmail.com>
Requires-Python: >=3.8
Classifier: Development Status :: 3 - Alpha
Classifier: Intended Audience :: Developers
Classifier: Intended Audience :: Science/Research
Classifier: License :: OSI Approved :: MIT License
Classifier: Programming Language :: Python :: 3
Classifier: Programming Language :: Python :: 3.8
Classifier: Programming Language :: Python :: 3.9
Classifier: Programming Language :: Python :: 3.10
Classifier: Topic :: Scientific/Engineering :: Artificial Intelligence
Classifier: Topic :: Scientific/Engineering :: Medical Science Apps.
License-File: LICENSE
Requires-Dist: antropy
Requires-Dist: imbalanced-learn
Requires-Dist: tensorflow[and-cuda]
Requires-Dist: matplotlib
Requires-Dist: mne
Requires-Dist: numpy
Requires-Dist: pandas
Requires-Dist: pyyaml
Requires-Dist: scikit-learn
Requires-Dist: scipy
Requires-Dist: seaborn
Requires-Dist: tqdm
Requires-Dist: pydot
Requires-Dist: pydot ; extra == "viz"
Project-URL: Bug Tracker, https://github.com/orabe/gaitmod/issues
Project-URL: Documentation, https://gaitmod.readthedocs.io/
Project-URL: Homepage, https://github.com/orabe/gaitmod
Project-URL: Repository, https://github.com/orabe/gaitmod
Provides-Extra: viz
